.gitignore
MANIFEST.in
README.rst
bootstrap.py
buildout.cfg
setup.cfg
setup.py
collective/__init__.py
collective.jqueryuithememanager.egg-info/PKG-INFO
collective.jqueryuithememanager.egg-info/SOURCES.txt
collective.jqueryuithememanager.egg-info/dependency_links.txt
collective.jqueryuithememanager.egg-info/entry_points.txt
collective.jqueryuithememanager.egg-info/namespace_packages.txt
collective.jqueryuithememanager.egg-info/not-zip-safe
collective.jqueryuithememanager.egg-info/requires.txt
collective.jqueryuithememanager.egg-info/top_level.txt
collective/jqueryuithememanager/__init__.py
collective/jqueryuithememanager/config.py
collective/jqueryuithememanager/configure.zcml
collective/jqueryuithememanager/i18n.py
collective/jqueryuithememanager/interfaces.py
collective/jqueryuithememanager/manager.py
collective/jqueryuithememanager/provider.py
collective/jqueryuithememanager/rebuild_i18n.sh
collective/jqueryuithememanager/registry.py
collective/jqueryuithememanager/testing.py
collective/jqueryuithememanager/theme.py
collective/jqueryuithememanager/vocabulary.py
collective/jqueryuithememanager/browser/__init__.py
collective/jqueryuithememanager/browser/configure.zcml
collective/jqueryuithememanager/browser/controlpanel.py
collective/jqueryuithememanager/browser/controlpanel_import.pt
collective/jqueryuithememanager/browser/controlpanel_layout.pt
collective/jqueryuithememanager/browser/controlpanel_main.pt
collective/jqueryuithememanager/browser/controlpanel_update.pt
collective/jqueryuithememanager/browser/jqueryui_icon.jpg
collective/jqueryuithememanager/browser/provider.py
collective/jqueryuithememanager/locales/collective.jqueryuithememanager.pot
collective/jqueryuithememanager/locales/fr/LC_MESSAGES/collective.jqueryuithememanager.po
collective/jqueryuithememanager/profiles/default/actions.xml
collective/jqueryuithememanager/profiles/default/browserlayer.xml
collective/jqueryuithememanager/profiles/default/metadata.xml
collective/jqueryuithememanager/profiles/default/registry.xml
collective/jqueryuithememanager/tests/__init__.py
collective/jqueryuithememanager/tests/base.py
collective/jqueryuithememanager/tests/test_functional.py
collective/jqueryuithememanager/tests/test_manager.py
collective/jqueryuithememanager/tests/test_provider.py
collective/jqueryuithememanager/tests/test_theme.py
collective/jqueryuithememanager/tests/theme.txt
collective/jqueryuithememanager/tests/utils.py
docs/HISTORY.txt
