Metadata-Version: 1.0
Name: collective.jqueryuithememanager
Version: 1.0
Summary: JQueryUI theme manager for Plone
Home-page: https://github.com/collective/collective.jqueryuithememanager
Author: JeanMichel FRANCOIS
Author-email: toutpt@gmail.com
License: GPL
Platform: UNKNOWN
Classifier: Framework :: Plone
Classifier: Programming Language :: Python
